{"sections":[],"abstract":[{"type":"text","text":"Introducción al Input del Usuario."}],"kind":"article","seeAlsoSections":[{"generated":true,"identifiers":["doc:\/\/KreatioDocs\/documentation\/KreatioDocs\/Variables-y-Tipos-de-Datos-en-KreatioDocs","doc:\/\/KreatioDocs\/documentation\/KreatioDocs\/Calculos-Matematicos-en-KreatioDocs","doc:\/\/KreatioDocs\/documentation\/KreatioDocs\/Funcion-Print"]}],"hierarchy":{"paths":[["doc:\/\/KreatioDocs\/documentation\/KreatioDocs","doc:\/\/KreatioDocs\/documentation\/KreatioDocs\/Programacion","doc:\/\/KreatioDocs\/documentation\/KreatioDocs\/Iniciando-el-Camino-en-Python-Essentials"]]},"identifier":{"url":"doc:\/\/KreatioDocs\/documentation\/KreatioDocs\/Obteniendo-Input-del-Usuario","interfaceLanguage":"swift"},"schemaVersion":{"major":0,"patch":0,"minor":3},"primaryContentSections":[{"content":[{"anchor":"Introducci%C3%B3n","type":"heading","level":2,"text":"Introducción"},{"type":"paragraph","inlineContent":[{"type":"text","text":"La "},{"type":"strong","inlineContent":[{"type":"text","text":"función"}]},{"type":"text","text":" incorporada "},{"code":"input","type":"codeVoice"},{"type":"text","text":" solicita y obtiene la entrada del usuario:"}]},{"code":["In [1]: name = input(\"¿Cuál es tu nombre? \")","¿Cuál es tu nombre? **KreatioDocs**","","In [2]: name","Out[2]: 'KreatioDocs'","","In [3]: print(name)","KreatioDocs"],"type":"codeListing","syntax":"python"},{"type":"paragraph","inlineContent":[{"identifier":"OIU1","type":"image"}]},{"anchor":"C%C3%B3mo-Funciona-input","type":"heading","level":3,"text":"Cómo Funciona `input`"},{"type":"paragraph","inlineContent":[{"type":"text","text":"El fragmento se ejecuta de la siguiente manera:"}]},{"type":"unorderedList","items":[{"content":[{"inlineContent":[{"text":"Primero, ","type":"text"},{"type":"codeVoice","code":"input"},{"text":" muestra su argumento de cadena, conocido como ","type":"text"},{"inlineContent":[{"type":"text","text":"prompt"}],"type":"strong"},{"text":", para indicarle al usuario qué escribir y espera una respuesta. Escribimos ","type":"text"},{"type":"codeVoice","code":"KreatioDocs"},{"text":" (sin comillas) y presionamos ","type":"text"},{"inlineContent":[{"type":"text","text":"Enter"}],"type":"strong"},{"text":". Usamos texto en ","type":"text"},{"type":"codeVoice","code":"negritas"},{"text":" para distinguir la entrada del usuario del texto del prompt que muestra ","type":"text"},{"type":"codeVoice","code":"input"},{"type":"text","text":"."}],"type":"paragraph"}]},{"content":[{"type":"paragraph","inlineContent":[{"text":"La función ","type":"text"},{"code":"input","type":"codeVoice"},{"text":" luego ","type":"text"},{"inlineContent":[{"type":"text","text":"devuelve"}],"type":"strong"},{"text":" (es decir, ","type":"text"},{"inlineContent":[{"text":"returns","type":"text"}],"type":"strong"},{"text":") esos caracteres como una cadena que el programa puede usar. Aquí asignamos esa cadena a la variable ","type":"text"},{"code":"name","type":"codeVoice"},{"text":".","type":"text"}]}]}]},{"anchor":"Consideraciones-al-Usar-input","type":"heading","level":3,"text":"Consideraciones al Usar `input`"},{"type":"paragraph","inlineContent":[{"type":"text","text":"El fragmento "},{"type":"codeVoice","code":"[2]"},{"type":"text","text":" muestra el valor de "},{"type":"codeVoice","code":"name"},{"type":"text","text":". Evaluar name muestra su valor entre comillas simples como ‘KreatioDocs’ porque es una cadena. Imprimir "},{"type":"codeVoice","code":"name"},{"type":"text","text":" (en el fragmento [3]) muestra la cadena sin las comillas. Si ingresas comillas, forman parte de la cadena, como en:"}]},{"code":["In [4]: name = input(\"¿Cuál es tu nombre? \")","¿Cuál es tu nombre? 'KreatioDocs'","","In [5]: name","Out[5]: \"'KreatioDocs'\"","","In [6]: print(name)","'KreatioDocs'"],"type":"codeListing","syntax":"python"},{"content":[{"type":"paragraph","inlineContent":[{"type":"text","text":"Siempre valida la entrada del usuario para evitar errores inesperados, especialmente cuando esperas un tipo específico de dato."}]}],"type":"aside","style":"tip","name":"Tip"},{"level":3,"type":"heading","anchor":"La-funci%C3%B3n-input-siempre-devuelve-una-cadena","text":"La función `input` siempre devuelve una cadena"},{"inlineContent":[{"text":"Considera los siguientes fragmentos que intentan leer dos números y sumarlos:","type":"text"}],"type":"paragraph"},{"code":["In [7]: value1 = input('Ingresa el primer número: ')","Ingresa el primer número: 7","","In [8]: value2 = input('Ingresa el segundo número: ')","Ingresa el segundo número: 3","","In [9]: value1 + value2","Out[9]: '73'"],"type":"codeListing","syntax":"python"},{"level":3,"type":"heading","anchor":"Obteniendo-un-entero-del-usuario","text":"Obteniendo un entero del usuario"},{"inlineContent":[{"type":"text","text":"En lugar de sumar los enteros "},{"type":"codeVoice","code":"7"},{"type":"text","text":" y "},{"type":"codeVoice","code":"3"},{"type":"text","text":" para producir "},{"type":"codeVoice","code":"10"},{"type":"text","text":", Python “suma” los valores de cadena "},{"type":"codeVoice","code":"'7'"},{"type":"text","text":" y "},{"type":"codeVoice","code":"'3'"},{"type":"text","text":", produciendo la cadena "},{"type":"codeVoice","code":"'73'"},{"type":"text","text":". Esto se conoce como "},{"type":"strong","inlineContent":[{"type":"text","text":"concatenación de strings."}]},{"type":"text","text":" Crea una nueva cadena que contiene el valor del operando izquierdo seguido del valor del operando derecho."}],"type":"paragraph"},{"inlineContent":[{"type":"text","text":"Si necesitas un entero, convierte la cadena a un entero usando la "},{"type":"strong","inlineContent":[{"type":"text","text":"función incorporada"}]},{"type":"text","text":" "},{"type":"codeVoice","code":"int"},{"type":"text","text":":"}],"type":"paragraph"},{"code":["In [10]: value = input('Ingresa un entero: ')","Ingresa un entero: 7","","In [11]: value = int(value)","","In [12]: value","Out[12]: 7"],"type":"codeListing","syntax":"python"},{"inlineContent":[{"inlineContent":[{"text":"Simplificación de la Conversión a Entero","type":"text"}],"type":"strong"}],"type":"paragraph"},{"inlineContent":[{"type":"text","text":"Podríamos haber combinado el código en los fragmentos "},{"type":"codeVoice","code":"[10]"},{"type":"text","text":" y "},{"type":"codeVoice","code":"[11]"},{"type":"text","text":":"}],"type":"paragraph"},{"code":["In [13]: another_value = int(input('Ingresa otro entero: '))","Ingresa otro entero: 13","","In [14]: another_value","Out[14]: 13"],"type":"codeListing","syntax":"python"},{"type":"aside","name":"Note","content":[{"inlineContent":[{"type":"text","text":"Es una buena práctica reducir la cantidad de pasos que el usuario tiene que realizar para completar una tarea, como combinar la entrada y la conversión en una sola línea."}],"type":"paragraph"}],"style":"note"},{"type":"paragraph","inlineContent":[{"type":"text","text":"Las variables "},{"type":"codeVoice","code":"value"},{"type":"text","text":" y "},{"type":"codeVoice","code":"another_value"},{"type":"text","text":" ahora contienen enteros. Sumarlos produce un resultado entero (en lugar de concatenarlos):"}]},{"type":"codeListing","syntax":"python","code":["In [15]: value + another_value","Out[15]: 20"]},{"type":"paragraph","inlineContent":[{"type":"strong","inlineContent":[{"text":"Manejo de Errores de Conversión","type":"text"}]}]},{"type":"paragraph","inlineContent":[{"text":"Si la cadena pasada a ","type":"text"},{"code":"int","type":"codeVoice"},{"text":" no se puede convertir a un entero, ocurre un ","type":"text"},{"code":"ValueError","type":"codeVoice"},{"text":":","type":"text"}]},{"type":"codeListing","syntax":"python","code":["## In [16]: bad_value = int(input('Ingresa otro entero: '))","Ingresa otro entero: hola","","ValueError                              Rastreo de error (llamada más reciente al final)","<ipython-input-16-cd36e6cf8911> en <module>()","----> 1 bad_value = int(input('Ingresa otro entero: '))","","ValueError: literal no válido para int() con base 10: 'hola'"]},{"type":"paragraph","inlineContent":[{"type":"strong","inlineContent":[{"type":"text","text":"Conversión de Punto Flotante a Entero"}]}]},{"type":"paragraph","inlineContent":[{"text":"La función ","type":"text"},{"code":"int","type":"codeVoice"},{"text":" también puede convertir un valor de punto flotante a un entero:","type":"text"}]},{"type":"codeListing","syntax":"python","code":["In [17]: int(10.5)","Out[17]: 10"]},{"type":"paragraph","inlineContent":[{"text":"Para convertir cadenas a números de punto flotante, usa la ","type":"text"},{"inlineContent":[{"text":"función","type":"text"}],"type":"strong"},{"text":" incorporada ","type":"text"},{"type":"codeVoice","code":"float"},{"text":".","type":"text"}]},{"type":"aside","name":"Tip","content":[{"type":"paragraph","inlineContent":[{"type":"text","text":"Utiliza el manejo de excepciones para controlar los errores de entrada y proporcionar mensajes de error claros al usuario."}]}],"style":"tip"},{"type":"paragraph","inlineContent":[{"identifier":"OIU2","type":"image"}]},{"type":"aside","name":"Note","content":[{"type":"paragraph","inlineContent":[{"type":"text","text":"Para convertir cadenas a números de punto flotante, usa la "},{"type":"strong","inlineContent":[{"type":"text","text":"función"}]},{"type":"text","text":" incorporada "},{"type":"strong","inlineContent":[{"type":"codeVoice","code":"float"}]},{"type":"text","text":"."}]}],"style":"note"},{"type":"paragraph","inlineContent":[{"type":"emphasis","inlineContent":[{"type":"text","text":"“En la programación, como en todo arte, la simplicidad es la clave del buen diseño.”"}]},{"type":"text","text":" - Edsger Dijkstra"}]}],"kind":"content"}],"variants":[{"traits":[{"interfaceLanguage":"swift"}],"paths":["\/documentation\/kreatiodocs\/obteniendo-input-del-usuario"]}],"metadata":{"role":"article","images":[{"identifier":"OIU1.png","type":"card"}],"roleHeading":"Artículo","title":"Obteniendo Input del Usuario","modules":[{"name":"KreatioDocs"}]},"references":{"doc://KreatioDocs/documentation/KreatioDocs/Iniciando-el-Camino-en-Python-Essentials":{"type":"topic","title":"Iniciando el Camino en Python - Essentials","kind":"article","abstract":[],"role":"collectionGroup","images":[{"type":"card","identifier":"ICPE.png"}],"identifier":"doc:\/\/KreatioDocs\/documentation\/KreatioDocs\/Iniciando-el-Camino-en-Python-Essentials","url":"\/documentation\/kreatiodocs\/iniciando-el-camino-en-python-essentials"},"FNPR1.png":{"identifier":"FNPR1.png","type":"image","alt":null,"variants":[{"url":"\/images\/KreatioDocs\/FNPR1.png","traits":["1x","light"]}]},"CMK1.png":{"identifier":"CMK1.png","type":"image","alt":null,"variants":[{"traits":["1x","light"],"url":"\/images\/KreatioDocs\/CMK1.png"}]},"OIU1":{"identifier":"OIU1","type":"image","alt":null,"variants":[{"url":"\/images\/KreatioDocs\/OIU1.png","traits":["1x","light"]}]},"doc://KreatioDocs/documentation/KreatioDocs/Programacion":{"identifier":"doc:\/\/KreatioDocs\/documentation\/KreatioDocs\/Programacion","type":"topic","title":"Programación","abstract":[],"role":"collectionGroup","url":"\/documentation\/kreatiodocs\/programacion","kind":"article","images":[{"type":"card","identifier":"PR_TOG.png"}]},"PR_TOG.png":{"identifier":"PR_TOG.png","type":"image","alt":null,"variants":[{"traits":["1x","light"],"url":"\/images\/KreatioDocs\/PR_TOG.png"}]},"OIU2":{"identifier":"OIU2","type":"image","alt":null,"variants":[{"url":"\/images\/KreatioDocs\/OIU2.png","traits":["1x","light"]}]},"doc://KreatioDocs/documentation/KreatioDocs/Variables-y-Tipos-de-Datos-en-KreatioDocs":{"abstract":[{"text":"Un viaje por el núcleo de la programación.","type":"text"}],"images":[{"identifier":"VTDK1.png","type":"card"}],"identifier":"doc:\/\/KreatioDocs\/documentation\/KreatioDocs\/Variables-y-Tipos-de-Datos-en-KreatioDocs","url":"\/documentation\/kreatiodocs\/variables-y-tipos-de-datos-en-kreatiodocs","kind":"article","title":"Variables y Tipos de Datos en KreatioDocs","type":"topic","role":"article"},"doc://KreatioDocs/documentation/KreatioDocs/Calculos-Matematicos-en-KreatioDocs":{"abstract":[{"type":"text","text":"La precisión de la aritmética en la programación."}],"images":[{"identifier":"CMK1.png","type":"card"}],"identifier":"doc:\/\/KreatioDocs\/documentation\/KreatioDocs\/Calculos-Matematicos-en-KreatioDocs","url":"\/documentation\/kreatiodocs\/calculos-matematicos-en-kreatiodocs","kind":"article","title":"Cálculos Matemáticos en KreatioDocs","type":"topic","role":"article"},"doc://KreatioDocs/documentation/KreatioDocs":{"type":"topic","url":"\/documentation\/kreatiodocs","abstract":[],"role":"collection","title":"KreatioDocs","kind":"symbol","identifier":"doc:\/\/KreatioDocs\/documentation\/KreatioDocs"},"doc://KreatioDocs/documentation/KreatioDocs/Funcion-Print":{"url":"\/documentation\/kreatiodocs\/funcion-print","type":"topic","role":"article","identifier":"doc:\/\/KreatioDocs\/documentation\/KreatioDocs\/Funcion-Print","kind":"article","abstract":[],"images":[{"identifier":"FNPR1.png","type":"card"}],"title":"Función Print"},"OIU1.png":{"identifier":"OIU1.png","type":"image","alt":null,"variants":[{"traits":["1x","light"],"url":"\/images\/KreatioDocs\/OIU1.png"}]},"VTDK1.png":{"identifier":"VTDK1.png","type":"image","alt":null,"variants":[{"url":"\/images\/KreatioDocs\/VTDK1.png","traits":["1x","light"]}]},"ICPE.png":{"identifier":"ICPE.png","type":"image","alt":null,"variants":[{"traits":["1x","light"],"url":"\/images\/KreatioDocs\/ICPE.png"}]}}}